HDL_Code/missionary_cannibal_complete.v
// Missionaries and Cannibals State Machine using T Flip-Flops
// This module implements the complete solution sequence

module missionary_cannibal_complete (
    input wire clk,
    input wire reset,
    input wire start,
    output reg [3:0] state,
    output reg [2:0] missionaries_left,
    output reg [2:0] cannibals_left,
    output reg [2:0] missionaries_right,
    output reg [2:0] cannibals_right,
    output reg boat_side,  // 0=left, 1=right
    output reg solution_complete,
    output reg valid_state
);

// State encoding for 12-step solution
parameter IDLE = 4'b0000;
parameter S1   = 4'b0001;  // Initial: M=3,C=3 | M=0,C=0, boat_left
parameter S2   = 4'b0010;  // After 1M,1C cross: M=2,C=2 | M=1,C=1, boat_right
parameter S3   = 4'b0011;  // After 1M returns: M=3,C=2 | M=0,C=1, boat_left
parameter S4   = 4'b0100;  // After 2C cross: M=3,C=0 | M=0,C=3, boat_right
parameter S5   = 4'b0101;  // After 1C returns: M=3,C=1 | M=0,C=2, boat_left
parameter S6   = 4'b0110;  // After 2M cross: M=1,C=1 | M=2,C=2, boat_right
parameter S7   = 4'b0111;  // After 1M,1C return: M=2,C=2 | M=1,C=1, boat_left
parameter S8   = 4'b1000;  // After 2M cross: M=0,C=2 | M=3,C=1, boat_right
parameter S9   = 4'b1001;  // After 1C returns: M=0,C=3 | M=3,C=0, boat_left
parameter S10  = 4'b1010;  // After 2C cross: M=0,C=1 | M=3,C=2, boat_right
parameter S11  = 4'b1011;  // After 1C returns: M=0,C=2 | M=3,C=1, boat_left
parameter S12  = 4'b1100;  // Final: M=0,C=0 | M=3,C=3, boat_right

// T Flip-Flop control signals - corrected logic for proper state progression
wire [3:0] t_ff;
wire enable_transition;
reg started;

// Track if the system has been started
always @(posedge clk or posedge reset) begin
    if (reset) begin
        started <= 0;
    end else if (start) begin
        started <= 1;
    end
end

// Enable transitions only when system is started and not in final state
assign enable_transition = started && (state != S12);

// T flip-flop logic based on binary counting with state-specific control
// The sequence progresses: 0000->0001->0010->0011->0100->0101->0110->0111->1000->1001->1010->1011->1100

// T[0] - LSB toggles every state transition (like a binary counter LSB)
assign t_ff[0] = enable_transition && (
    (state == IDLE) ||           // 0000 -> 0001
    (state == S1) ||             // 0001 -> 0010
    (state == S2) ||             // 0010 -> 0011
    (state == S3) ||             // 0011 -> 0100
    (state == S4) ||             // 0100 -> 0101
    (state == S5) ||             // 0101 -> 0110
    (state == S6) ||             // 0110 -> 0111
    (state == S7) ||             // 0111 -> 1000
    (state == S8) ||             // 1000 -> 1001
    (state == S9) ||             // 1001 -> 1010
    (state == S10) ||            // 1010 -> 1011
    (state == S11)               // 1011 -> 1100
);

// T[1] - Second bit toggles when LSB goes from 1 to 0 (every 2 transitions)
assign t_ff[1] = enable_transition && (
    (state == S1) ||             // 0001 -> 0010
    (state == S3) ||             // 0011 -> 0100
    (state == S5) ||             // 0101 -> 0110
    (state == S7) ||             // 0111 -> 1000
    (state == S9) ||             // 1001 -> 1010
    (state == S11)               // 1011 -> 1100
);

// T[2] - Third bit toggles when lower 2 bits go from 11 to 00 (every 4 transitions)
assign t_ff[2] = enable_transition && (
    (state == S3) ||             // 0011 -> 0100
    (state == S7) ||             // 0111 -> 1000
    (state == S11)               // 1011 -> 1100
);

// T[3] - MSB toggles when lower 3 bits go from 111 to 000 (every 8 transitions)
assign t_ff[3] = enable_transition && (
    (state == S7)                // 0111 -> 1000
);

// Note: We stop at S12 (1100) which represents the final state

// T Flip-Flop implementation
always @(posedge clk or posedge reset) begin
    if (reset) begin
        state <= IDLE;
    end else begin
        state[0] <= state[0] ^ t_ff[0];
        state[1] <= state[1] ^ t_ff[1];
        state[2] <= state[2] ^ t_ff[2];
        state[3] <= state[3] ^ t_ff[3];
    end
end

// Output logic for missionaries and cannibals positions
always @(*) begin
    case (state)
        IDLE: begin
            missionaries_left = 3; cannibals_left = 3;
            missionaries_right = 0; cannibals_right = 0;
            boat_side = 0; solution_complete = 0; valid_state = 1;
        end
        S1: begin
            missionaries_left = 3; cannibals_left = 3;
            missionaries_right = 0; cannibals_right = 0;
            boat_side = 0; solution_complete = 0; valid_state = 1;
        end
        S2: begin
            missionaries_left = 2; cannibals_left = 2;
            missionaries_right = 1; cannibals_right = 1;
            boat_side = 1; solution_complete = 0; valid_state = 1;
        end
        S3: begin
            missionaries_left = 3; cannibals_left = 2;
            missionaries_right = 0; cannibals_right = 1;
            boat_side = 0; solution_complete = 0; valid_state = 1;
        end
        S4: begin
            missionaries_left = 3; cannibals_left = 0;
            missionaries_right = 0; cannibals_right = 3;
            boat_side = 1; solution_complete = 0; valid_state = 1;
        end
        S5: begin
            missionaries_left = 3; cannibals_left = 1;
            missionaries_right = 0; cannibals_right = 2;
            boat_side = 0; solution_complete = 0; valid_state = 1;
        end
        S6: begin
            missionaries_left = 1; cannibals_left = 1;
            missionaries_right = 2; cannibals_right = 2;
            boat_side = 1; solution_complete = 0; valid_state = 1;
        end
        S7: begin
            missionaries_left = 2; cannibals_left = 2;
            missionaries_right = 1; cannibals_right = 1;
            boat_side = 0; solution_complete = 0; valid_state = 1;
        end
        S8: begin
            missionaries_left = 0; cannibals_left = 2;
            missionaries_right = 3; cannibals_right = 1;
            boat_side = 1; solution_complete = 0; valid_state = 1;
        end
        S9: begin
            missionaries_left = 0; cannibals_left = 3;
            missionaries_right = 3; cannibals_right = 0;
            boat_side = 0; solution_complete = 0; valid_state = 1;
        end
        S10: begin
            missionaries_left = 0; cannibals_left = 1;
            missionaries_right = 3; cannibals_right = 2;
            boat_side = 1; solution_complete = 0; valid_state = 1;
        end
        S11: begin
            missionaries_left = 0; cannibals_left = 2;
            missionaries_right = 3; cannibals_right = 1;
            boat_side = 0; solution_complete = 0; valid_state = 1;
        end
        S12: begin
            missionaries_left = 0; cannibals_left = 0;
            missionaries_right = 3; cannibals_right = 3;
            boat_side = 1; solution_complete = 1; valid_state = 1;
        end
        default: begin
            missionaries_left = 0; cannibals_left = 0;
            missionaries_right = 0; cannibals_right = 0;
            boat_side = 0; solution_complete = 0; valid_state = 0;
        end
    endcase
end

endmodule

HDL_Code/tb_missionary_cannibal_complete.v
// Testbench for Missionaries and Cannibals State Machine
// Comprehensive verification including timing analysis

`timescale 1ns/1ps

module tb_missionary_cannibal_complete;

// Testbench signals
reg clk;
reg reset;
reg start;
wire [3:0] state;
wire [2:0] missionaries_left;
wire [2:0] cannibals_left;
wire [2:0] missionaries_right;
wire [2:0] cannibals_right;
wire boat_side;
wire solution_complete;
wire valid_state;

// Clock period definition
parameter CLK_PERIOD = 10; // 10ns = 100MHz

// Instantiate the Unit Under Test (UUT)
missionary_cannibal_complete uut (
    .clk(clk),
    .reset(reset),
    .start(start),
    .state(state),
    .missionaries_left(missionaries_left),
    .cannibals_left(cannibals_left),
    .missionaries_right(missionaries_right),
    .cannibals_right(cannibals_right),
    .boat_side(boat_side),
    .solution_complete(solution_complete),
    .valid_state(valid_state)
);

// Clock generation
initial begin
    clk = 0;
    forever #(CLK_PERIOD/2) clk = ~clk;
end

// Test sequence
integer i;
initial begin
    // Initialize signals
    reset = 1;
    start = 0;
    
    // Create VCD file for waveform viewing
    $dumpfile("missionary_cannibal_simulation.vcd");
    $dumpvars(0, tb_missionary_cannibal_complete);
    
    // Display header
    $display("=== Missionaries and Cannibals State Machine Simulation ===");
    $display("Time\tState\tM_L\tC_L\tM_R\tC_R\tBoat\tComplete\tValid");
    $display("----\t-----\t---\t---\t---\t---\t----\t--------\t-----");
    
    // Reset sequence
    #20 reset = 0;
    #10;
    
    // Monitor initial state
    $display("%4t\t%4b\t%3d\t%3d\t%3d\t%3d\t%4s\t%8b\t%5b", 
             $time, state, missionaries_left, cannibals_left, 
             missionaries_right, cannibals_right, 
             boat_side ? "Right" : "Left", solution_complete, valid_state);
    
    // Test invalid state scenarios first (for waveform demonstration)
    $display("\n=== TESTING INVALID INPUT SCENARIOS ===");
    
    // Force invalid state 4'b1101 (not in solution set)
    force uut.state = 4'b1101;
    #CLK_PERIOD;
    $display("%4t\t%4b\t%3d\t%3d\t%3d\t%3d\t%4s\t%8b\t%5b - INVALID STATE", 
             $time, state, missionaries_left, cannibals_left, 
             missionaries_right, cannibals_right, 
             boat_side ? "Right" : "Left", solution_complete, valid_state);
    
    // Force another invalid state 4'b1110
    force uut.state = 4'b1110;
    #CLK_PERIOD;
    $display("%4t\t%4b\t%3d\t%3d\t%3d\t%3d\t%4s\t%8b\t%5b - INVALID STATE", 
             $time, state, missionaries_left, cannibals_left, 
             missionaries_right, cannibals_right, 
             boat_side ? "Right" : "Left", solution_complete, valid_state);
    
    // Force invalid state 4'b1111
    force uut.state = 4'b1111;
    #CLK_PERIOD;
    $display("%4t\t%4b\t%3d\t%3d\t%3d\t%3d\t%4s\t%8b\t%5b - INVALID STATE", 
             $time, state, missionaries_left, cannibals_left, 
             missionaries_right, cannibals_right, 
             boat_side ? "Right" : "Left", solution_complete, valid_state);
    
    // Release the force and reset to start normal operation
    release uut.state;
    reset = 1;
    #CLK_PERIOD;
    reset = 0;
    #CLK_PERIOD;
    
    $display("\n=== STARTING NORMAL SOLUTION SEQUENCE ===");
    
    // Start the solution sequence
    start = 1;
    #CLK_PERIOD;
    start = 0;
    
    // Wait for solution to complete or timeout after 15 cycles (12 states + margin)
    for (i = 0; i < 15; i = i + 1) begin
        #CLK_PERIOD;
        $display("%4t\t%4b\t%3d\t%3d\t%3d\t%3d\t%4s\t%8b\t%5b", 
                 $time, state, missionaries_left, cannibals_left, 
                 missionaries_right, cannibals_right, 
                 boat_side ? "Right" : "Left", solution_complete, valid_state);
        
        // Check for solution completion
        if (solution_complete) begin
            $display("\n*** SOLUTION COMPLETED SUCCESSFULLY! ***");
            $display("Final State: All 3 missionaries and 3 cannibals on right side");
            i = 15; // Exit loop by setting i to loop limit
        end
    end
    
    // Additional time to observe final state
    #(5*CLK_PERIOD);
    
    // Verification checks
    $display("\n=== VERIFICATION RESULTS ===");
    
    // Check final state
    if (missionaries_right == 3 && cannibals_right == 3 && 
        missionaries_left == 0 && cannibals_left == 0) begin
        $display("✓ PASS: Final positioning correct");
    end else begin
        $display("✗ FAIL: Final positioning incorrect");
    end
    
    // Check solution complete flag
    if (solution_complete) begin
        $display("✓ PASS: Solution complete flag set");
    end else begin
        $display("✗ FAIL: Solution complete flag not set");
    end
    
    // Check validity
    if (valid_state) begin
        $display("✓ PASS: Valid state maintained");
    end else begin
        $display("✗ FAIL: Invalid state detected");
    end
    
    $display("\n=== TIMING ANALYSIS ===");
    $display("Clock Period: %0d ns", CLK_PERIOD);
    $display("Total Simulation Time: %0t", $time);
    $display("Number of Clock Cycles: %0d", ($time / CLK_PERIOD));
    
    // Test reset functionality
    $display("\n=== TESTING RESET FUNCTIONALITY ===");
    #20;
    reset = 1;
    #CLK_PERIOD;
    reset = 0;
    #CLK_PERIOD;
    
    if (state == 4'b0000 && !solution_complete) begin
        $display("✓ PASS: Reset functionality working");
    end else begin
        $display("✗ FAIL: Reset functionality not working");
    end
    
    $display("\n=== SIMULATION COMPLETED ===");
    $finish;
end

// State change monitor
always @(posedge clk) begin
    if (!reset && $time > 30) begin // Skip initial reset period
        case (state)
            4'b0001: $display("State S1: Initial setup - boat on left");
            4'b0010: $display("State S2: 1M,1C crossed to right");
            4'b0011: $display("State S3: 1M returned to left");
            4'b0100: $display("State S4: 2C crossed to right");
            4'b0101: $display("State S5: 1C returned to left");
            4'b0110: $display("State S6: 2M crossed to right");
            4'b0111: $display("State S7: 1M,1C returned to left");
            4'b1000: $display("State S8: 2M crossed to right");
            4'b1001: $display("State S9: 1C returned to left");
            4'b1010: $display("State S10: 2C crossed to right");
            4'b1011: $display("State S11: 1C returned to left");
            4'b1100: $display("State S12: SOLUTION COMPLETE!");
        endcase
    end
end

// Safety constraint checker
always @(*) begin
    if (!reset && valid_state) begin
        // Check missionaries >= cannibals on each side (when missionaries > 0)
        if ((missionaries_left > 0 && missionaries_left < cannibals_left) ||
            (missionaries_right > 0 && missionaries_right < cannibals_right)) begin
            $display("WARNING: Safety constraint violated at time %t!", $time);
            $display("Left side: M=%d, C=%d | Right side: M=%d, C=%d", 
                     missionaries_left, cannibals_left, missionaries_right, cannibals_right);
        end
    end
end

// Performance monitoring - simplified version
real start_time, end_time, execution_time;
reg performance_measured;
initial begin
    performance_measured = 0;
    wait(start == 1);
    start_time = $time;
end

// Monitor for solution completion
always @(posedge solution_complete) begin
    if (!performance_measured) begin
        end_time = $time;
        execution_time = end_time - start_time;
        $display("\n=== PERFORMANCE METRICS ===");
        $display("Execution Time: %.2f ns", execution_time);
        $display("Clock Cycles to Complete: %0d", (execution_time / CLK_PERIOD));
        performance_measured = 1;
    end
end

endmodule

Simulation_Results/missionary_cannibal_simulation.vcd
$date
	Sun Jun 15 20:53:22 2025
$end
$version
	Icarus Verilog
$end
$timescale
	1ps
$end
$scope module tb_missionary_cannibal_complete $end
$var wire 1 ! valid_state $end
$var wire 4 " state [3:0] $end
$var wire 1 # solution_complete $end
$var wire 3 $ missionaries_right [2:0] $end
$var wire 3 % missionaries_left [2:0] $end
$var wire 3 & cannibals_right [2:0] $end
$var wire 3 ' cannibals_left [2:0] $end
$var wire 1 ( boat_side $end
$var parameter 32 ) CLK_PERIOD $end
$var reg 1 * clk $end
$var reg 1 + performance_measured $end
$var reg 1 , reset $end
$var reg 1 - start $end
$var real 1 . end_time $end
$var real 1 / execution_time $end
$var integer 32 0 i [31:0] $end
$var real 1 1 start_time $end
$scope module uut $end
$var wire 1 * clk $end
$var wire 1 2 enable_transition $end
$var wire 1 , reset $end
$var wire 1 - start $end
$var wire 4 3 t_ff [3:0] $end
$var parameter 4 4 IDLE $end
$var parameter 4 5 S1 $end
$var parameter 4 6 S10 $end
$var parameter 4 7 S11 $end
$var parameter 4 8 S12 $end
$var parameter 4 9 S2 $end
$var parameter 4 : S3 $end
$var parameter 4 ; S4 $end
$var parameter 4 < S5 $end
$var parameter 4 = S6 $end
$var parameter 4 > S7 $end
$var parameter 4 ? S8 $end
$var parameter 4 @ S9 $end
$var reg 1 ( boat_side $end
$var reg 3 A cannibals_left [2:0] $end
$var reg 3 B cannibals_right [2:0] $end
$var reg 3 C missionaries_left [2:0] $end
$var reg 3 D missionaries_right [2:0] $end
$var reg 1 # solution_complete $end
$var reg 1 E started $end
$var reg 4 F state [3:0] $end
$var reg 1 ! valid_state $end
$upscope $end
$upscope $end
$enddefinitions $end
$comment Show the parameter values. $end
$dumpall
b1001 @
b1000 ?
b111 >
b110 =
b101 <
b100 ;
b11 :
b10 9
b1100 8
b1011 7
b1010 6
b1 5
b0 4
b1010 )
$end
#0
$dumpvars
b0 F
0E
b0 D
b11 C
b0 B
b11 A
b0 3
02
r0 1
bx 0
r0 /
r0 .
0-
1,
0+
0*
0(
b11 '
b0 &
b11 %
b0 $
0#
b0 "
1!
$end
#5000
1*
#10000
0*
#15000
1*
#20000
0*
0,
#25000
1*
#30000
0!
b0 '
b0 A
b0 %
b0 C
0*
b1101 "
b1101 F
#35000
b1101 "
b1101 F
1*
#40000
0*
b1110 "
b1110 F
#45000
b1110 "
b1110 F
1*
#50000
0*
b1111 "
b1111 F
#55000
b1111 "
b1111 F
1*
#60000
1!
b11 '
b11 A
b11 %
b11 C
b0 "
b0 F
0*
1,
#65000
1*
#70000
0*
0,
#75000
1*
#80000
r80 1
0*
1-
#85000
b1 3
12
1E
1*
#90000
0*
b0 0
0-
#95000
b11 3
b1 "
b1 F
1*
#100000
0*
b1 0
#105000
b1 3
1(
b1 &
b1 B
b1 $
b1 D
b10 '
b10 A
b10 %
b10 C
b10 "
b10 F
1*
#110000
0*
b10 0
#115000
b111 3
0(
b0 $
b0 D
b11 %
b11 C
b11 "
b11 F
1*
#120000
0*
b11 0
#125000
b1 3
1(
b11 &
b11 B
b0 '
b0 A
b100 "
b100 F
1*
#130000
0*
b100 0
#135000
b11 3
0(
b10 &
b10 B
b1 '
b1 A
b101 "
b101 F
1*
#140000
0*
b101 0
#145000
b1 3
1(
b10 $
b10 D
b1 %
b1 C
b110 "
b110 F
1*
#150000
0*
b110 0
#155000
0(
b1 &
b1 B
b1 $
b1 D
b10 '
b10 A
b10 %
b10 C
b1111 3
b111 "
b111 F
1*
#160000
0*
b111 0
#165000
1(
b11 $
b11 D
b0 %
b0 C
b1 3
b1000 "
b1000 F
1*
#170000
0*
b1000 0
#175000
b11 3
0(
b0 &
b0 B
b11 '
b11 A
b1001 "
b1001 F
1*
#180000
0*
b1001 0
#185000
b1 3
1(
b10 &
b10 B
b1 '
b1 A
b1010 "
b1010 F
1*
#190000
0*
b1010 0
#195000
b111 3
0(
b1 &
b1 B
b10 '
b10 A
b1011 "
b1011 F
1*
#200000
0*
b1011 0
#205000
1+
r125 /
r205 .
b0 3
02
1#
1(
b11 &
b11 B
b0 '
b0 A
b1100 "
b1100 F
1*
#210000
0*
b10000 0
#215000
1*
#220000
0*
#225000
1*
#230000
0*
#235000
1*
#240000
0*
#245000
1*
#250000
0*
#255000
1*
#260000
0*
#265000
1*
#270000
0*
#275000
1*
#280000
0#
0(
b0 &
b0 B
b0 $
b0 D
b11 '
b11 A
b11 %
b11 C
0E
b0 "
b0 F
0*
1,
#285000
1*
#290000
0*
0,
