VerilogFiles/missionary_cannibal_sequential.v
// ==========================================================================================
// COSE221 : Term Project 2 : Missionaries and Cannibals Sequential Logic
// Sequential FSM Implementation for Missionary-Cannibal Problem
// Author: Niccolas Parra
// Date: 2025-06-14
// 
// DESIGN OVERVIEW:
// - FSM with 12 valid states representing puzzle configurations
// - Automatic progression through solution path
// - Synchronous reset to initial state
// - Positive edge-triggered clock
// - Outputs: missionary_next, cannibal_next, finish
// ==========================================================================================

module missionary_cannibal_sequential (
    input wire clock,                    // System clock (positive edge triggered)
    input wire reset,                    // Synchronous reset (active high)
    output reg [1:0] missionary_next,    // Next missionaries on original side
    output reg [1:0] cannibal_next,      // Next cannibals on original side  
    output reg [2:0] finish              // Finish signal (3-bit as specified)
);

    // ===============================
    // STATE ENCODING
    // ===============================
    // 4-bit state encoding for 12 valid states
    // State represents (missionaries_left, cannibals_left, boat_side)
    // boat_side: 0 = left, 1 = right
    
    parameter [3:0] STATE_0  = 4'b0000;  // (3,3,L) - Initial state
    parameter [3:0] STATE_1  = 4'b0001;  // (3,1,R) - After first move
    parameter [3:0] STATE_2  = 4'b0010;  // (3,2,L) - After return
    parameter [3:0] STATE_3  = 4'b0011;  // (3,0,R) - Remove 2 cannibals
    parameter [3:0] STATE_4  = 4'b0100;  // (3,1,L) - Return 1 cannibal
    parameter [3:0] STATE_5  = 4'b0101;  // (1,1,R) - Move 2 missionaries
    parameter [3:0] STATE_6  = 4'b0110;  // (2,2,L) - Return 1M+1C
    parameter [3:0] STATE_7  = 4'b0111;  // (0,2,R) - Move 2 missionaries
    parameter [3:0] STATE_8  = 4'b1000;  // (0,3,L) - Return 1 cannibal
    parameter [3:0] STATE_9  = 4'b1001;  // (0,1,R) - Move 2 cannibals
    parameter [3:0] STATE_10 = 4'b1010;  // (0,2,L) - Return 1 cannibal
    parameter [3:0] STATE_11 = 4'b1011;  // (0,0,R) - Final state
    
    // Current state register
    reg [3:0] current_state;
    reg [3:0] next_state;
    
    // ===============================
    // STATE REGISTER
    // ===============================
    // Synchronous state update with positive edge clock
    always @(posedge clock) begin
        if (reset) begin
            current_state <= STATE_0;  // Reset to initial state (3,3,L)
        end else begin
            current_state <= next_state;
        end
    end
    
    // ===============================
    // NEXT STATE LOGIC
    // ===============================
    // Sequential progression through valid solution path
    always @(*) begin
        case (current_state)
            STATE_0:  next_state = STATE_1;   // (3,3,L) -> (3,1,R)
            STATE_1:  next_state = STATE_2;   // (3,1,R) -> (3,2,L)
            STATE_2:  next_state = STATE_3;   // (3,2,L) -> (3,0,R)
            STATE_3:  next_state = STATE_4;   // (3,0,R) -> (3,1,L)
            STATE_4:  next_state = STATE_5;   // (3,1,L) -> (1,1,R)
            STATE_5:  next_state = STATE_6;   // (1,1,R) -> (2,2,L)
            STATE_6:  next_state = STATE_7;   // (2,2,L) -> (0,2,R)
            STATE_7:  next_state = STATE_8;   // (0,2,R) -> (0,3,L)
            STATE_8:  next_state = STATE_9;   // (0,3,L) -> (0,1,R)
            STATE_9:  next_state = STATE_10;  // (0,1,R) -> (0,2,L)
            STATE_10: next_state = STATE_11;  // (0,2,L) -> (0,0,R)
            STATE_11: next_state = STATE_0;   // (0,0,R) -> (3,3,L) - Auto reset
            default:  next_state = STATE_0;   // Error recovery
        endcase
    end
    
    // ===============================
    // OUTPUT LOGIC (Moore Machine)
    // ===============================
    // Outputs depend only on current state
    always @(*) begin
        case (current_state)
            STATE_0: begin  // (3,3,L)
                missionary_next = 2'b11;  // 3 missionaries
                cannibal_next = 2'b11;    // 3 cannibals
                finish = 3'b000;          // Not finished
            end
            STATE_1: begin  // (3,1,R)
                missionary_next = 2'b11;  // 3 missionaries
                cannibal_next = 2'b01;    // 1 cannibal
                finish = 3'b000;          // Not finished
            end
            STATE_2: begin  // (3,2,L)
                missionary_next = 2'b11;  // 3 missionaries
                cannibal_next = 2'b10;    // 2 cannibals
                finish = 3'b000;          // Not finished
            end
            STATE_3: begin  // (3,0,R)
                missionary_next = 2'b11;  // 3 missionaries
                cannibal_next = 2'b00;    // 0 cannibals
                finish = 3'b000;          // Not finished
            end
            STATE_4: begin  // (3,1,L)
                missionary_next = 2'b11;  // 3 missionaries
                cannibal_next = 2'b01;    // 1 cannibal
                finish = 3'b000;          // Not finished
            end
            STATE_5: begin  // (1,1,R)
                missionary_next = 2'b01;  // 1 missionary
                cannibal_next = 2'b01;    // 1 cannibal
                finish = 3'b000;          // Not finished
            end
            STATE_6: begin  // (2,2,L)
                missionary_next = 2'b10;  // 2 missionaries
                cannibal_next = 2'b10;    // 2 cannibals
                finish = 3'b000;          // Not finished
            end
            STATE_7: begin  // (0,2,R)
                missionary_next = 2'b00;  // 0 missionaries
                cannibal_next = 2'b10;    // 2 cannibals
                finish = 3'b000;          // Not finished
            end
            STATE_8: begin  // (0,3,L)
                missionary_next = 2'b00;  // 0 missionaries
                cannibal_next = 2'b11;    // 3 cannibals
                finish = 3'b000;          // Not finished
            end
            STATE_9: begin  // (0,1,R)
                missionary_next = 2'b00;  // 0 missionaries
                cannibal_next = 2'b01;    // 1 cannibal
                finish = 3'b000;          // Not finished
            end
            STATE_10: begin // (0,2,L)
                missionary_next = 2'b00;  // 0 missionaries
                cannibal_next = 2'b10;    // 2 cannibals
                finish = 3'b000;          // Not finished
            end
            STATE_11: begin // (0,0,R) - FINAL STATE
                missionary_next = 2'b00;  // 0 missionaries
                cannibal_next = 2'b00;    // 0 cannibals
                finish = 3'b001;          // FINISHED!
            end
            default: begin   // Error state
                missionary_next = 2'b11;  // Reset values
                cannibal_next = 2'b11;
                finish = 3'b000;
            end
        endcase
    end
    
endmodule

// ==========================================================================================
// DESIGN NOTES:
// 
// 1. FSM TYPE: Moore machine - outputs depend only on current state
// 2. CLOCK: Positive edge-triggered, synchronous design
// 3. RESET: Synchronous reset, returns to initial state (3,3,L)
// 4. STATES: 12 valid states representing the optimal solution path
// 5. PROGRESSION: Automatic advancement through solution sequence
// 6. FINISH: 3-bit signal, active (001) only in final state
// 7. AUTO-RESTART: From final state, automatically returns to initial state
// 
// STATE SEQUENCE (Optimal Solution):
// (3,3,L) -> (3,1,R) -> (3,2,L) -> (3,0,R) -> (3,1,L) -> (1,1,R) ->
// (2,2,L) -> (0,2,R) -> (0,3,L) -> (0,1,R) -> (0,2,L) -> (0,0,R)
// 
// TIMING: Each state transition occurs on rising clock edge
// OPTIMIZATION: State encoding optimized for synthesis efficiency
// ==========================================================================================

VerilogFiles/tb_missionary_cannibal_sequential.v
// ==========================================================================================
// TESTBENCH for Missionary-Cannibal Sequential Logic
// Comprehensive verification of FSM behavior
// Author: Niccolas Parra
// Date: 2025-06-14
// ==========================================================================================

`timescale 1ns / 1ps

module tb_missionary_cannibal_sequential;

    // ===============================
    // TESTBENCH SIGNALS
    // ===============================
    reg clock;
    reg reset;
    wire [1:0] missionary_next;
    wire [1:0] cannibal_next;
    wire [2:0] finish;
    
    // Test control variables
    integer cycle_count;
    integer error_count;
    
    // ===============================
    // DEVICE UNDER TEST (DUT)
    // ===============================
    missionary_cannibal_sequential dut (
        .clock(clock),
        .reset(reset),
        .missionary_next(missionary_next),
        .cannibal_next(cannibal_next),
        .finish(finish)
    );
    
    // ===============================
    // CLOCK GENERATION
    // ===============================
    // 100MHz clock (10ns period)
    initial begin
        clock = 0;
        forever #5 clock = ~clock;  // Toggle every 5ns
    end
    
    // ===============================
    // EXPECTED STATE SEQUENCE
    // ===============================
    // Define expected outputs for each state
    reg [1:0] expected_missionary [0:11];
    reg [1:0] expected_cannibal [0:11];
    reg [2:0] expected_finish [0:11];
    
    initial begin
        // STATE_0: (3,3,L)
        expected_missionary[0] = 2'b11; expected_cannibal[0] = 2'b11; expected_finish[0] = 3'b000;
        // STATE_1: (3,1,R)
        expected_missionary[1] = 2'b11; expected_cannibal[1] = 2'b01; expected_finish[1] = 3'b000;
        // STATE_2: (3,2,L)
        expected_missionary[2] = 2'b11; expected_cannibal[2] = 2'b10; expected_finish[2] = 3'b000;
        // STATE_3: (3,0,R)
        expected_missionary[3] = 2'b11; expected_cannibal[3] = 2'b00; expected_finish[3] = 3'b000;
        // STATE_4: (3,1,L)
        expected_missionary[4] = 2'b11; expected_cannibal[4] = 2'b01; expected_finish[4] = 3'b000;
        // STATE_5: (1,1,R)
        expected_missionary[5] = 2'b01; expected_cannibal[5] = 2'b01; expected_finish[5] = 3'b000;
        // STATE_6: (2,2,L)
        expected_missionary[6] = 2'b10; expected_cannibal[6] = 2'b10; expected_finish[6] = 3'b000;
        // STATE_7: (0,2,R)
        expected_missionary[7] = 2'b00; expected_cannibal[7] = 2'b10; expected_finish[7] = 3'b000;
        // STATE_8: (0,3,L)
        expected_missionary[8] = 2'b00; expected_cannibal[8] = 2'b11; expected_finish[8] = 3'b000;
        // STATE_9: (0,1,R)
        expected_missionary[9] = 2'b00; expected_cannibal[9] = 2'b01; expected_finish[9] = 3'b000;
        // STATE_10: (0,2,L)
        expected_missionary[10] = 2'b00; expected_cannibal[10] = 2'b10; expected_finish[10] = 3'b000;
        // STATE_11: (0,0,R) - FINAL
        expected_missionary[11] = 2'b00; expected_cannibal[11] = 2'b00; expected_finish[11] = 3'b001;
    end
    
    // ===============================
    // VERIFICATION TASK
    // ===============================
    task verify_state;
        input integer state_num;
        begin
            if (missionary_next !== expected_missionary[state_num] ||
                cannibal_next !== expected_cannibal[state_num] ||
                finish !== expected_finish[state_num]) begin
                
                $display("ERROR at cycle %0d, state %0d:", cycle_count, state_num);
                $display("  Expected: M=%b, C=%b, F=%b", 
                    expected_missionary[state_num], expected_cannibal[state_num], expected_finish[state_num]);
                $display("  Actual:   M=%b, C=%b, F=%b", 
                    missionary_next, cannibal_next, finish);
                error_count = error_count + 1;
            end else begin
                $display("PASS cycle %0d, state %0d: M=%b, C=%b, F=%b", 
                    cycle_count, state_num, missionary_next, cannibal_next, finish);
            end
        end
    endtask
    
    // ===============================
    // MAIN TEST SEQUENCE
    // ===============================
    initial begin
        // Initialize
        error_count = 0;
        cycle_count = 0;
        reset = 0;
        
        $display("======================================");
        $display("MISSIONARY-CANNIBAL SEQUENTIAL TEST");
        $display("======================================");
        
        // Wait for clock stabilization
        #10;
        
        // ===== TEST 1: RESET FUNCTIONALITY =====
        $display("\nTEST 1: Reset Functionality");
        reset = 1;
        @(posedge clock);
        #1; // Small delay for combinational logic
        verify_state(0); // Should be in initial state
        reset = 0;
        
        // ===== TEST 2: COMPLETE SEQUENCE =====
        $display("\nTEST 2: Complete Solution Sequence");
        
        // Verify initial state first
        #1;
        verify_state(0);
        
        // Run through complete 12-state sequence
        for (cycle_count = 1; cycle_count < 12; cycle_count = cycle_count + 1) begin
            @(posedge clock);
            #1; // Small delay for combinational logic
            verify_state(cycle_count);
        end
        
        // ===== TEST 3: AUTO-RESTART =====
        $display("\nTEST 3: Auto-restart from finish state");
        @(posedge clock);
        #1;
        verify_state(0); // Should be back to initial state
        
        // ===== TEST 4: RESET DURING OPERATION =====
        $display("\nTEST 4: Reset during operation");
        
        // Run a few cycles
        repeat(5) begin
            @(posedge clock);
            cycle_count = cycle_count + 1;
        end
        
        // Apply reset
        reset = 1;
        @(posedge clock);
        #1;
        verify_state(0); // Should be in initial state
        reset = 0;
        
        // ===== TEST 5: EXTENDED OPERATION =====
        $display("\nTEST 5: Extended operation (2 complete cycles)");
        
        // Run two complete sequences
        for (cycle_count = 0; cycle_count < 24; cycle_count = cycle_count + 1) begin
            @(posedge clock);
            #1;
            verify_state(cycle_count % 12);
        end
        
        // ===== TEST RESULTS =====
        $display("\n======================================");
        if (error_count == 0) begin
            $display("ALL TESTS PASSED! ✓");
            $display("Sequential FSM is working correctly.");
        end else begin
            $display("TESTS FAILED! ✗");
            $display("Total errors: %0d", error_count);
        end
        $display("======================================");
        
        // Finish simulation
        #100;
        $finish;
    end
    
    // ===============================
    // WAVEFORM DUMP (for viewing)
    // ===============================
    initial begin
        $dumpfile("missionary_cannibal_sequential.vcd");
        $dumpvars(0, tb_missionary_cannibal_sequential);
    end
    
    // ===============================
    // MONITORING (for debugging)
    // ===============================
    initial begin
        $monitor("Time=%0t | Clock=%b | Reset=%b | State=%b | M=%b C=%b F=%b", 
                 $time, clock, reset, dut.current_state, missionary_next, cannibal_next, finish);
    end
    
endmodule

// ==========================================================================================
// TESTBENCH FEATURES:
// 
// 1. COMPREHENSIVE TESTING:
//    - Reset functionality
//    - Complete solution sequence
//    - Auto-restart behavior
//    - Reset during operation
//    - Extended operation
// 
// 2. VERIFICATION:
//    - Expected vs actual output comparison
//    - Error counting and reporting
//    - Detailed pass/fail information
// 
// 3. DEBUGGING SUPPORT:
//    - Waveform generation (VCD file)
//    - Real-time monitoring
//    - Detailed error messages
// 
// 4. TIMING:
//    - 100MHz clock (realistic frequency)
//    - Proper setup/hold timing
//    - Combinational delay consideration
// 
// USAGE:
//   1. Compile: iverilog -o test tb_missionary_cannibal_sequential.v missionary_cannibal_sequential.v
//   2. Run: ./test
//   3. View waveforms: gtkwave missionary_cannibal_sequential.vcd
// ==========================================================================================

SimulationFiles/missionary_cannibal_sequential.vcd
$date
	Sun Jun 15 06:25:31 2025
$end
$version
	Icarus Verilog
$end
$timescale
	1ps
$end
$scope module tb_missionary_cannibal_sequential $end
$var wire 2 ! missionary_next [1:0] $end
$var wire 3 " finish [2:0] $end
$var wire 2 # cannibal_next [1:0] $end
$var reg 1 $ clock $end
$var reg 1 % reset $end
$var integer 32 & cycle_count [31:0] $end
$var integer 32 ' error_count [31:0] $end
$scope module dut $end
$var wire 1 $ clock $end
$var wire 1 % reset $end
$var parameter 4 ( STATE_0 $end
$var parameter 4 ) STATE_1 $end
$var parameter 4 * STATE_10 $end
$var parameter 4 + STATE_11 $end
$var parameter 4 , STATE_2 $end
$var parameter 4 - STATE_3 $end
$var parameter 4 . STATE_4 $end
$var parameter 4 / STATE_5 $end
$var parameter 4 0 STATE_6 $end
$var parameter 4 1 STATE_7 $end
$var parameter 4 2 STATE_8 $end
$var parameter 4 3 STATE_9 $end
$var reg 2 4 cannibal_next [1:0] $end
$var reg 4 5 current_state [3:0] $end
$var reg 3 6 finish [2:0] $end
$var reg 2 7 missionary_next [1:0] $end
$var reg 4 8 next_state [3:0] $end
$upscope $end
$scope task verify_state $end
$var integer 32 9 state_num [31:0] $end
$upscope $end
$upscope $end
$enddefinitions $end
$comment Show the parameter values. $end
$dumpall
b1001 3
b1000 2
b111 1
b110 0
b101 /
b100 .
b11 -
b10 ,
b1011 +
b1010 *
b1 )
b0 (
$end
#0
$dumpvars
bx 9
bx 8
bx 7
bx 6
bx 5
bx 4
b0 '
b0 &
0%
0$
bx #
bx "
bx !
$end
#5000
1$
#10000
0$
1%
#15000
b0 "
b0 6
b11 #
b11 4
b11 !
b11 7
b1 8
b0 5
1$
#16000
0%
b0 9
#17000
b1 &
#20000
0$
#25000
b10 8
b1 #
b1 4
b1 5
1$
#26000
b10 &
b1 9
#30000
0$
#35000
b10 #
b10 4
b11 8
b10 5
1$
#36000
b11 &
b10 9
#40000
0$
#45000
b100 8
b0 #
b0 4
b11 5
1$
#46000
b100 &
b11 9
#50000
0$
#55000
b1 #
b1 4
b101 8
b100 5
1$
#56000
b101 &
b100 9
#60000
0$
#65000
b110 8
b1 !
b1 7
b101 5
1$
#66000
b110 &
b101 9
#70000
0$
#75000
b10 #
b10 4
b10 !
b10 7
b111 8
b110 5
1$
#76000
b111 &
b110 9
#80000
0$
#85000
b1000 8
b0 !
b0 7
b111 5
1$
#86000
b1000 &
b111 9
#90000
0$
#95000
b11 #
b11 4
b1001 8
b1000 5
1$
#96000
b1001 &
b1000 9
#100000
0$
#105000
b1010 8
b1 #
b1 4
b1001 5
1$
#106000
b1010 &
b1001 9
#110000
0$
#115000
b10 #
b10 4
b1011 8
b1010 5
1$
#116000
b1011 &
b1010 9
#120000
0$
#125000
b0 8
b1 "
b1 6
b0 #
b0 4
b1011 5
1$
#126000
b1100 &
b1011 9
#130000
0$
#135000
b0 "
b0 6
b11 #
b11 4
b11 !
b11 7
b1 8
b0 5
1$
#136000
b0 9
#140000
0$
#145000
b10 8
b1 #
b1 4
b1 5
b1101 &
1$
#150000
0$
#155000
b10 #
b10 4
b11 8
b10 5
b1110 &
1$
#160000
0$
#165000
b100 8
b0 #
b0 4
b11 5
b1111 &
1$
#170000
0$
#175000
b1 #
b1 4
b101 8
b100 5
b10000 &
1$
#180000
0$
#185000
b1 8
b11 #
b11 4
b0 5
1%
b10001 &
1$
#190000
0$
#195000
1$
#196000
b0 &
0%
#200000
0$
#205000
b1 #
b1 4
b10 8
b1 5
1$
#206000
b1 &
b1 '
#210000
0$
#215000
b11 8
b10 #
b10 4
b10 5
1$
#216000
b10 &
b10 '
b1 9
#220000
0$
#225000
b0 #
b0 4
b100 8
b11 5
1$
#226000
b11 &
b11 '
b10 9
#230000
0$
#235000
b101 8
b1 #
b1 4
b100 5
1$
#236000
b100 &
b100 '
b11 9
#240000
0$
#245000
b1 !
b1 7
b110 8
b101 5
1$
#246000
b101 &
b101 '
b100 9
#250000
0$
#255000
b111 8
b10 #
b10 4
b10 !
b10 7
b110 5
1$
#256000
b110 &
b110 '
b101 9
#260000
0$
#265000
b0 !
b0 7
b1000 8
b111 5
1$
#266000
b111 &
b111 '
b110 9
#270000
0$
#275000
b1001 8
b11 #
b11 4
b1000 5
1$
#276000
b1000 &
b1000 '
b111 9
#280000
0$
#285000
b1 #
b1 4
b1010 8
b1001 5
1$
#286000
b1001 &
b1001 '
b1000 9
#290000
0$
#295000
b1011 8
b10 #
b10 4
b1010 5
1$
#296000
b1010 &
b1010 '
b1001 9
#300000
0$
#305000
b1 "
b1 6
b0 #
b0 4
b0 8
b1011 5
1$
#306000
b1011 &
b1011 '
b1010 9
#310000
0$
#315000
b1 8
b0 "
b0 6
b11 #
b11 4
b11 !
b11 7
b0 5
1$
#316000
b1100 &
b1100 '
b1011 9
#320000
0$
#325000
b1 #
b1 4
b10 8
b1 5
1$
#326000
b1101 &
b1101 '
b0 9
#330000
0$
#335000
b11 8
b10 #
b10 4
b10 5
1$
#336000
b1110 &
b1110 '
b1 9
#340000
0$
#345000
b0 #
b0 4
b100 8
b11 5
1$
#346000
b1111 &
b1111 '
b10 9
#350000
0$
#355000
b101 8
b1 #
b1 4
b100 5
1$
#356000
b10000 &
b10000 '
b11 9
#360000
0$
#365000
b1 !
b1 7
b110 8
b101 5
1$
#366000
b10001 &
b10001 '
b100 9
#370000
0$
#375000
b111 8
b10 #
b10 4
b10 !
b10 7
b110 5
1$
#376000
b10010 &
b10010 '
b101 9
#380000
0$
#385000
b0 !
b0 7
b1000 8
b111 5
1$
#386000
b10011 &
b10011 '
b110 9
#390000
0$
#395000
b1001 8
b11 #
b11 4
b1000 5
1$
#396000
b10100 &
b10100 '
b111 9
#400000
0$
#405000
b1 #
b1 4
b1010 8
b1001 5
1$
#406000
b10101 &
b10101 '
b1000 9
#410000
0$
#415000
b1011 8
b10 #
b10 4
b1010 5
1$
#416000
b10110 &
b10110 '
b1001 9
#420000
0$
#425000
b1 "
b1 6
b0 #
b0 4
b0 8
b1011 5
1$
#426000
b10111 &
b10111 '
b1010 9
#430000
0$
#435000
b1 8
b0 "
b0 6
b11 #
b11 4
b11 !
b11 7
b0 5
1$
#436000
b11000 &
b11000 '
b1011 9
#440000
0$
#445000
b1 #
b1 4
b10 8
b1 5
1$
#450000
0$
#455000
b11 8
b10 #
b10 4
b10 5
1$
#460000
0$
#465000
b0 #
b0 4
b100 8
b11 5
1$
#470000
0$
#475000
b101 8
b1 #
b1 4
b100 5
1$
#480000
0$
#485000
b1 !
b1 7
b110 8
b101 5
1$
#490000
0$
#495000
b111 8
b10 #
b10 4
b10 !
b10 7
b110 5
1$
#500000
0$
#505000
b0 !
b0 7
b1000 8
b111 5
1$
#510000
0$
#515000
b1001 8
b11 #
b11 4
b1000 5
1$
#520000
0$
#525000
b1 #
b1 4
b1010 8
b1001 5
1$
#530000
0$
#535000
b1011 8
b10 #
b10 4
b1010 5
1$
